Metadata-Version: 2.1
Name: egen111222-my-first-new-projectisfhifsidyifg
Version: 1.0
Summary: Описание Вашего проекта
Author: Kirill
Author-email: 123@gmail.com
